Argumentor/Argument.py
Argumentor/ArgumentValidation.py
Argumentor/Argumentor.py
Argumentor/Command.py
Argumentor/Flag.py
Argumentor/Result.py
Argumentor/__init__.py
argumentor_gardehal-0.0.2.dist-info/licenses/LICENSE
argumentor_gardehal-0.0.2.dist-info/METADATA
argumentor_gardehal-0.0.2.dist-info/WHEEL
argumentor_gardehal-0.0.2.dist-info/top_level.txt
argumentor_gardehal-0.0.2.dist-info/RECORD
