Metadata-Version: 2.4
Name: argumentor_gardehal
Version: 0.0.2
Summary: CLI argument parsing, validation, documentation
Home-page: https://github.com/gardehal/argumentor
Author: Gardehal
Author-email: alethogar@protonmail.com
License: MIT
Classifier: Programming Language :: Python :: 3
Classifier: License :: OSI Approved :: MIT License
Classifier: Operating System :: OS Independent
License-File: LICENSE
Dynamic: author
Dynamic: author-email
Dynamic: classifier
Dynamic: description
Dynamic: description-content-type
Dynamic: home-page
Dynamic: license
Dynamic: license-file
Dynamic: summary
